keras_buoy/ResumableModel.py
keras_buoy/__init__.py
keras_buoy/callbacks.py
keras_buoy/models.py
keras_buoy/utils.py
keras_buoy-0.1.2.dist-info/AUTHORS.rst
keras_buoy-0.1.2.dist-info/LICENSE.txt
keras_buoy-0.1.2.dist-info/METADATA
keras_buoy-0.1.2.dist-info/WHEEL
keras_buoy-0.1.2.dist-info/top_level.txt
keras_buoy-0.1.2.dist-info/RECORD
