Metadata-Version: 2.1
Name: keras-buoy
Version: 0.1.2
Summary: Keras wrapper that autosaves what ModelCheckpoint cannot.
Home-page: https://github.com/dorukkarinca/keras-buoy/
Author: Doruk Karınca
Author-email: dorukkarinca@gmail.com
License: mit
Platform: any
Classifier: Development Status :: 4 - Beta
Classifier: Programming Language :: Python
Requires-Dist: tensorflow (>=2.0)
Provides-Extra: testing
Requires-Dist: pytest ; extra == 'testing'
Requires-Dist: pytest-cov ; extra == 'testing'
